vsi/__init__.py
vsi/main.py
vsi_cli-1.0.5.dist-info/METADATA
vsi_cli-1.0.5.dist-info/WHEEL
vsi_cli-1.0.5.dist-info/entry_points.txt
vsi_cli-1.0.5.dist-info/top_level.txt
vsi_cli-1.0.5.dist-info/RECORD
