Metadata-Version: 2.4
Name: vsi-cli
Version: 1.0.5
Summary: vsi cli | aws cli wrapper
Home-page: https://gitlab.spectrumflow.net/C-Ermias.Girmai/vsi-cli
Author: ermiasgirmai
Author-email: c-ermias.girmai@charter.com
Classifier: Programming Language :: Python :: 3
Classifier: Operating System :: OS Independent
Requires-Python: >=3.7
Requires-Dist: typer>=0.9.0
Dynamic: author
Dynamic: author-email
Dynamic: classifier
Dynamic: description
Dynamic: description-content-type
Dynamic: home-page
Dynamic: requires-dist
Dynamic: requires-python
Dynamic: summary
